pypilot/__init__.py
pypilot/__main__.py
pypilot/agent/base.py
pypilot/agent/chat.py
pypilot/agent/code.py
pypilot/agent/prompt.py
pypilot/agent/python_chat.py
pypilot/agent/router.py
pypilot/cli.py
pypilot/console.py
pypilot/oai_utils.py
pypilot/parser.py
pypilot/utils.py
pypilot/version.py
python_pilot-0.0.11.dist-info/LICENSE
python_pilot-0.0.11.dist-info/METADATA
python_pilot-0.0.11.dist-info/WHEEL
python_pilot-0.0.11.dist-info/entry_points.txt
python_pilot-0.0.11.dist-info/RECORD
