Metadata-Version: 2.1
Name: python-pilot
Version: 0.0.11
Summary: A python terminal with coding copilot inside
Home-page: https://github.com/roy-pstr/python-pilot
Author: Roy Pasternak
Author-email: roy@larium.ai
Requires-Python: >=3.9,<4.0
Classifier: Programming Language :: Python :: 3
Classifier: Programming Language :: Python :: 3.9
Classifier: Programming Language :: Python :: 3.10
Classifier: Programming Language :: Python :: 3.11
Provides-Extra: llama
Requires-Dist: huggingface-hub (>=0.21.4,<0.22.0) ; extra == "llama"
Requires-Dist: llama-cpp-python[server] (>=0.2.56,<0.3.0) ; extra == "llama"
Requires-Dist: numpy (>=1.26.4,<2.0.0)
Requires-Dist: openai (>=1.13.3,<2.0.0)
Requires-Dist: python-dotenv (>=1.0.1,<2.0.0)
Requires-Dist: tiktoken (>=0.6.0,<0.7.0)
